compas/__init__.py
compas/__main__.py
compas/_iotools.py
compas/_os.py
compas/itertools.py
compas/linalg.py
compas/matrices.py
compas/plugins.py
compas/tolerance.py
compas/colors/__init__.py
compas/colors/color.py
compas/colors/colordict.py
compas/colors/colormap.py
compas/colors/html_colors.py
compas/colors/mpl_colormap.py
compas/colors/cmcrameri/acton.txt
compas/colors/cmcrameri/actonS.txt
compas/colors/cmcrameri/bam.txt
compas/colors/cmcrameri/bamO.txt
compas/colors/cmcrameri/bamako.txt
compas/colors/cmcrameri/bamakoS.txt
compas/colors/cmcrameri/batlow.txt
compas/colors/cmcrameri/batlowK.txt
compas/colors/cmcrameri/batlowS.txt
compas/colors/cmcrameri/batlowW.txt
compas/colors/cmcrameri/berlin.txt
compas/colors/cmcrameri/bilbao.txt
compas/colors/cmcrameri/bilbaoS.txt
compas/colors/cmcrameri/broc.txt
compas/colors/cmcrameri/brocO.txt
compas/colors/cmcrameri/buda.txt
compas/colors/cmcrameri/budaS.txt
compas/colors/cmcrameri/bukavu.txt
compas/colors/cmcrameri/cork.txt
compas/colors/cmcrameri/corkO.txt
compas/colors/cmcrameri/davos.txt
compas/colors/cmcrameri/davosS.txt
compas/colors/cmcrameri/devon.txt
compas/colors/cmcrameri/devonS.txt
compas/colors/cmcrameri/fes.txt
compas/colors/cmcrameri/grayC.txt
compas/colors/cmcrameri/grayCS.txt
compas/colors/cmcrameri/hawaii.txt
compas/colors/cmcrameri/hawaiiS.txt
compas/colors/cmcrameri/imola.txt
compas/colors/cmcrameri/imolaS.txt
compas/colors/cmcrameri/lajolla.txt
compas/colors/cmcrameri/lajollaS.txt
compas/colors/cmcrameri/lapaz.txt
compas/colors/cmcrameri/lapazS.txt
compas/colors/cmcrameri/lisbon.txt
compas/colors/cmcrameri/nuuk.txt
compas/colors/cmcrameri/nuukS.txt
compas/colors/cmcrameri/oleron.txt
compas/colors/cmcrameri/oslo.txt
compas/colors/cmcrameri/osloS.txt
compas/colors/cmcrameri/roma.txt
compas/colors/cmcrameri/romaO.txt
compas/colors/cmcrameri/tofino.txt
compas/colors/cmcrameri/tokyo.txt
compas/colors/cmcrameri/tokyoS.txt
compas/colors/cmcrameri/turku.txt
compas/colors/cmcrameri/turkuS.txt
compas-2.14.0.dist-info/licenses/AUTHORS.md
compas-2.14.0.dist-info/licenses/LICENSE
compas-2.14.0.dist-info/METADATA
compas-2.14.0.dist-info/WHEEL
compas-2.14.0.dist-info/entry_points.txt
compas-2.14.0.dist-info/top_level.txt
compas-2.14.0.dist-info/RECORD
