Metadata-Version: 2.4
Name: compas
Version: 2.14.0
Summary: The main COMPAS framework library.
Author-email: tom van mele <tom.v.mele@gmail.com>
License: MIT License
Project-URL: Homepage, https://compas-dev.github.io/compas
Project-URL: Documentation, https://compas-dev.github.io/compas
Project-URL: Repository, https://github.com/compas-dev/compas.git
Project-URL: Changelog, https://github.com/compas-dev/compas/blob/main/CHANGELOG.md
Project-URL: Issues, https://github.com/compas-dev/compas/issues
Project-URL: Forum, https://forum.compas-framework.org/
Keywords: architecture,engineering,fabrication,construction
Classifier: Development Status :: 5 - Production/Stable
Classifier: Topic :: Scientific/Engineering
Classifier: Operating System :: Unix
Classifier: Operating System :: POSIX
Classifier: Operating System :: Microsoft :: Windows
Classifier: Programming Language :: Python
Classifier: Programming Language :: Python :: 3
Classifier: Programming Language :: Python :: 3.9
Classifier: Programming Language :: Python :: 3.10
Classifier: Programming Language :: Python :: 3.11
Classifier: Programming Language :: Python :: 3.12
Requires-Python: >=3.9
License-File: LICENSE
License-File: AUTHORS.md
Requires-Dist: jsonschema
Requires-Dist: networkx>=3.0
Requires-Dist: numpy>=1.15.4
Requires-Dist: scipy>=1.1
Requires-Dist: watchdog; sys_platform != "emscripten"
Provides-Extra: dev
Requires-Dist: attrs>=17.4; extra == "dev"
Requires-Dist: black>=22.12.0; extra == "dev"
Requires-Dist: bump-my-version; extra == "dev"
Requires-Dist: compas_invocations2; extra == "dev"
Requires-Dist: invoke>=0.14; extra == "dev"
Requires-Dist: pytest-cov; extra == "dev"
Requires-Dist: ruff; extra == "dev"
Requires-Dist: sphinx_compas2_theme; extra == "dev"
Requires-Dist: twine; extra == "dev"
Requires-Dist: wheel; extra == "dev"
Requires-Dist: pythonnet; extra == "dev"
Dynamic: license-file
